{
    "parameters": {
        "base_rating": 1500,
        "k_factor": 55,
        "home_advantage": 30,
        "default_home_advantage": 30.0,
        "interstate_home_advantage": 90.0,
        "margin_factor": 0.2,
        "season_carryover": 0.6,
        "max_margin": 80,
        "beta": 0.05,
        "team_states": {}
    },
    "team_ratings": {
        "Carlton": 1458.9485770742947,
        "Essendon": 1319.414138502917,
        "Geelong": 1676.596852023122,
        "North Melbourne": 1288.6320942059888,
        "Brisbane Lions": 1751.0496152873761,
        "West Coast": 1183.1184072137235,
        "Western Bulldogs": 1618.0401411740922,
        "Richmond": 1258.9824716062067,
        "Melbourne": 1417.8432271281033,
        "St Kilda": 1416.1894403732292,
        "Fitzroy": 1499.9998740247572,
        "Sydney": 1520.9336586742525,
        "Hawthorn": 1654.947395359763,
        "Collingwood": 1626.034040513748,
        "Adelaide": 1617.8164493456968,
        "Fremantle": 1585.7120463641018,
        "Port Adelaide": 1432.2293684799383,
        "Gold Coast": 1567.75176380396,
        "Greater Western Sydney": 1605.7604388447294
    },
    "yearly_ratings": {
        "1990": {
            "Carlton": 1516.1509715038312,
            "Essendon": 1642.925887775654,
            "Geelong": 1426.759345527823,
            "North Melbourne": 1565.5628426084545,
            "Brisbane Lions": 1322.441510882916,
            "West Coast": 1597.6583695508737,
            "Western Bulldogs": 1500.3654071330504,
            "Richmond": 1377.9386421368793,
            "Melbourne": 1586.0013209036676,
            "St Kilda": 1457.4234202477855,
            "Fitzroy": 1400.7925789343335,
            "Sydney": 1293.0172669896274,
            "Hawthorn": 1599.7557222791415,
            "Collingwood": 1713.2067135259626,
            "Adelaide": 1500,
            "Fremantle": 1500,
            "Port Adelaide": 1500,
            "Gold Coast": 1500,
            "Greater Western Sydney": 1500
        },
        "1991_start": {
            "Carlton": 1509.6905829022987,
            "Essendon": 1585.7555326653924,
            "Geelong": 1456.0556073166938,
            "North Melbourne": 1539.3377055650726,
            "Brisbane Lions": 1393.4649065297497,
            "West Coast": 1558.5950217305242,
            "Western Bulldogs": 1500.2192442798303,
            "Richmond": 1426.7631852821276,
            "Melbourne": 1551.6007925422007,
            "St Kilda": 1474.4540521486713,
            "Fitzroy": 1440.4755473606,
            "Sydney": 1375.8103601937764,
            "Hawthorn": 1559.853433367485,
            "Collingwood": 1627.9240281155776,
            "Adelaide": 1500.0,
            "Fremantle": 1500.0,
            "Port Adelaide": 1500.0,
            "Gold Coast": 1500.0,
            "Greater Western Sydney": 1500.0
        },
        "1991": {
            "Carlton": 1408.6522472759575,
            "Essendon": 1541.275450446446,
            "Geelong": 1646.2522432557162,
            "North Melbourne": 1477.4068280945235,
            "Brisbane Lions": 1275.2699498067489,
            "West Coast": 1729.2395797255917,
            "Western Bulldogs": 1468.2227862413854,
            "Richmond": 1364.3506487317009,
            "Melbourne": 1577.0122349355456,
            "St Kilda": 1574.559834170592,
            "Fitzroy": 1303.0955041647553,
            "Sydney": 1339.833916766172,
            "Hawthorn": 1717.7545541835987,
            "Collingwood": 1598.2907236321767,
            "Adelaide": 1478.7834985690902,
            "Fremantle": 1500.0,
            "Port Adelaide": 1500.0,
            "Gold Coast": 1500.0,
            "Greater Western Sydney": 1500.0
        },
        "1992_start": {
            "Carlton": 1445.1913483655744,
            "Essendon": 1524.7652702678677,
            "Geelong": 1587.7513459534298,
            "North Melbourne": 1486.4440968567142,
            "Brisbane Lions": 1365.1619698840493,
            "West Coast": 1637.5437478353551,
            "Western Bulldogs": 1480.9336717448311,
            "Richmond": 1418.6103892390206,
            "Melbourne": 1546.2073409613274,
            "St Kilda": 1544.7359005023552,
            "Fitzroy": 1381.8573024988532,
            "Sydney": 1403.9003500597032,
            "Hawthorn": 1630.6527325101592,
            "Collingwood": 1558.974434179306,
            "Adelaide": 1487.270099141454,
            "Fremantle": 1500.0,
            "Port Adelaide": 1500.0,
            "Gold Coast": 1500.0,
            "Greater Western Sydney": 1500.0
        },
        "1992": {
            "Carlton": 1566.3514371613262,
            "Essendon": 1527.1869678540268,
            "Geelong": 1652.568379968707,
            "North Melbourne": 1403.987827612288,
            "Brisbane Lions": 1287.6332377950466,
            "West Coast": 1738.837587168508,
            "Western Bulldogs": 1596.0684206826027,
            "Richmond": 1300.799151503766,
            "Melbourne": 1463.4597019427795,
            "St Kilda": 1593.9869374822786,
            "Fitzroy": 1375.5611424973486,
            "Sydney": 1218.4454632798718,
            "Hawthorn": 1647.842214878717,
            "Collingwood": 1612.600589048871,
            "Adelaide": 1514.670941123863,
            "Fremantle": 1500.0,
            "Port Adelaide": 1500.0,
            "Gold Coast": 1500.0,
            "Greater Western Sydney": 1500.0
        },
        "1993_start": {
            "Carlton": 1539.8108622967957,
            "Essendon": 1516.312180712416,
            "Geelong": 1591.5410279812243,
            "North Melbourne": 1442.3926965673727,
            "Brisbane Lions": 1372.579942677028,
            "West Coast": 1643.3025523011047,
            "Western Bulldogs": 1557.6410524095616,
            "Richmond": 1380.4794909022596,
            "Melbourne": 1478.0758211656678,
            "St Kilda": 1556.3921624893671,
            "Fitzroy": 1425.3366854984092,
            "Sydney": 1331.067277967923,
            "Hawthorn": 1588.70532892723,
            "Collingwood": 1567.5603534293225,
            "Adelaide": 1508.8025646743179,
            "Fremantle": 1500.0,
            "Port Adelaide": 1500.0,
            "Gold Coast": 1500.0,
            "Greater Western Sydney": 1500.0
        },
        "1993": {
            "Carlton": 1613.0140686572558,
            "Essendon": 1645.2314974033393,
            "Geelong": 1639.8628685328258,
            "North Melbourne": 1539.4552536080841,
            "Brisbane Lions": 1270.7947991240487,
            "West Coast": 1633.6211987665079,
            "Western Bulldogs": 1541.9954785643606,
            "Richmond": 1285.36290593581,
            "Melbourne": 1505.5370196403042,
            "St Kilda": 1517.571902942567,
            "Fitzroy": 1435.367959944062,
            "Sydney": 1201.5055084078617,
            "Hawthorn": 1585.34250995607,
            "Collingwood": 1520.7891917028333,
            "Adelaide": 1564.5478368140693,
            "Fremantle": 1500.0,
            "Port Adelaide": 1500.0,
            "Gold Coast": 1500.0,
            "Greater Western Sydney": 1500.0
        },
        "1994_start": {
            "Carlton": 1567.8084411943535,
            "Essendon": 1587.1388984420037,
            "Geelong": 1583.9177211196954,
            "North Melbourne": 1523.6731521648505,
            "Brisbane Lions": 1362.4768794744293,
            "West Coast": 1580.1727192599046,
            "Western Bulldogs": 1525.1972871386163,
            "Richmond": 1371.217743561486,
            "Melbourne": 1503.3222117841824,
            "St Kilda": 1510.5431417655402,
            "Fitzroy": 1461.2207759664373,
            "Sydney": 1320.903305044717,
            "Hawthorn": 1551.205505973642,
            "Collingwood": 1512.4735150217,
            "Adelaide": 1538.7287020884417,
            "Fremantle": 1500.0,
            "Port Adelaide": 1500.0,
            "Gold Coast": 1500.0,
            "Greater Western Sydney": 1500.0
        },
        "1994": {
            "Carlton": 1610.1990891582498,
            "Essendon": 1515.622845120229,
            "Geelong": 1610.294259301765,
            "North Melbourne": 1619.9368310926804,
            "Brisbane Lions": 1408.6200755882624,
            "West Coast": 1698.855642121311,
            "Western Bulldogs": 1550.7548824419416,
            "Richmond": 1453.231819030462,
            "Melbourne": 1588.3025049074333,
            "St Kilda": 1375.978590887826,
            "Fitzroy": 1295.562859804124,
            "Sydney": 1237.5529984073312,
            "Hawthorn": 1559.2615263646915,
            "Collingwood": 1520.1612058265587,
            "Adelaide": 1455.664869947134,
            "Fremantle": 1500.0,
            "Port Adelaide": 1500.0,
            "Gold Coast": 1500.0,
            "Greater Western Sydney": 1500.0
        },
        "1995_start": {
            "Carlton": 1566.1194534949498,
            "Essendon": 1509.3737070721374,
            "Geelong": 1566.176555581059,
            "North Melbourne": 1571.9620986556083,
            "Brisbane Lions": 1445.1720453529574,
            "West Coast": 1619.3133852727865,
            "Western Bulldogs": 1530.452929465165,
            "Richmond": 1471.9390914182773,
            "Melbourne": 1552.98150294446,
            "St Kilda": 1425.5871545326956,
            "Fitzroy": 1377.3377158824744,
            "Sydney": 1342.5317990443987,
            "Hawthorn": 1535.5569158188148,
            "Collingwood": 1512.0967234959353,
            "Adelaide": 1473.3989219682805,
            "Fremantle": 1500.0,
            "Port Adelaide": 1500.0,
            "Gold Coast": 1500.0,
            "Greater Western Sydney": 1500.0
        },
        "1995": {
            "Carlton": 1765.4267312190184,
            "Essendon": 1585.4018290890062,
            "Geelong": 1682.0570918792946,
            "North Melbourne": 1631.5493710659352,
            "Brisbane Lions": 1479.5533959539987,
            "West Coast": 1608.3955694008398,
            "Western Bulldogs": 1481.230589184194,
            "Richmond": 1535.9844822809848,
            "Melbourne": 1481.3564838624475,
            "St Kilda": 1419.0990552884825,
            "Fitzroy": 1200.9143653072358,
            "Sydney": 1406.1407071196277,
            "Hawthorn": 1422.2997386330042,
            "Collingwood": 1461.073139910544,
            "Adelaide": 1401.5698628703858,
            "Fremantle": 1437.9475869350008,
            "Port Adelaide": 1500.0,
            "Gold Coast": 1500.0,
            "Greater Western Sydney": 1500.0
        },
        "1996_start": {
            "Carlton": 1659.256038731411,
            "Essendon": 1551.2410974534037,
            "Geelong": 1609.2342551275767,
            "North Melbourne": 1578.929622639561,
            "Brisbane Lions": 1487.7320375723991,
            "West Coast": 1565.0373416405039,
            "Western Bulldogs": 1488.7383535105164,
            "Richmond": 1521.5906893685908,
            "Melbourne": 1488.8138903174686,
            "St Kilda": 1451.4594331730896,
            "Fitzroy": 1320.5486191843415,
            "Sydney": 1443.6844242717766,
            "Hawthorn": 1453.3798431798025,
            "Collingwood": 1476.6438839463262,
            "Adelaide": 1440.9419177222314,
            "Fremantle": 1462.7685521610006,
            "Port Adelaide": 1500.0,
            "Gold Coast": 1500.0,
            "Greater Western Sydney": 1500.0
        },
        "1996": {
            "Carlton": 1589.246290034136,
            "Essendon": 1635.543770548383,
            "Geelong": 1570.2832821258055,
            "North Melbourne": 1685.5469621145398,
            "Brisbane Lions": 1596.519018629607,
            "West Coast": 1618.6744429072874,
            "Western Bulldogs": 1380.6462086793097,
            "Richmond": 1547.263022590747,
            "Melbourne": 1410.1977044025518,
            "St Kilda": 1463.6258959168715,
            "Fitzroy": 1158.1001241877545,
            "Sydney": 1608.9821606102253,
            "Hawthorn": 1483.723380224163,
            "Collingwood": 1483.4191484448374,
            "Adelaide": 1365.5443287594057,
            "Fremantle": 1402.684259824375,
            "Port Adelaide": 1500.0,
            "Gold Coast": 1500.0,
            "Greater Western Sydney": 1500.0
        },
        "1997_start": {
            "Carlton": 1553.5477740204817,
            "Essendon": 1581.3262623290298,
            "Geelong": 1542.1699692754833,
            "North Melbourne": 1611.328177268724,
            "Brisbane Lions": 1557.9114111777642,
            "West Coast": 1571.2046657443725,
            "Western Bulldogs": 1428.3877252075858,
            "Richmond": 1528.357813554448,
            "Melbourne": 1446.1186226415311,
            "St Kilda": 1478.175537550123,
            "Fitzroy": 1294.8600745126528,
            "Sydney": 1565.389296366135,
            "Hawthorn": 1490.2340281344977,
            "Collingwood": 1490.0514890669024,
            "Adelaide": 1419.3265972556435,
            "Fremantle": 1441.610555894625,
            "Port Adelaide": 1500.0,
            "Gold Coast": 1500.0,
            "Greater Western Sydney": 1500.0
        },
        "1997": {
            "Carlton": 1510.8456509415762,
            "Essendon": 1462.2227477256497,
            "Geelong": 1602.9616049516512,
            "North Melbourne": 1616.9083841133656,
            "Brisbane Lions": 1537.446617493327,
            "West Coast": 1572.567145144325,
            "Western Bulldogs": 1555.1099791098934,
            "Richmond": 1459.2166545242899,
            "Melbourne": 1301.54807247282,
            "St Kilda": 1646.746827298143,
            "Fitzroy": 1294.8600745126528,
            "Sydney": 1559.5363054597685,
            "Hawthorn": 1405.7580369571097,
            "Collingwood": 1493.9911172179654,
            "Adelaide": 1600.6718863091903,
            "Fremantle": 1412.7614544912092,
            "Port Adelaide": 1466.847441277063,
            "Gold Coast": 1500.0,
            "Greater Western Sydney": 1500.0
        },
        "1998_start": {
            "Carlton": 1506.5073905649458,
            "Essendon": 1477.3336486353899,
            "Geelong": 1561.7769629709908,
            "North Melbourne": 1570.1450304680193,
            "Brisbane Lions": 1522.4679704959963,
            "West Coast": 1543.540287086595,
            "Western Bulldogs": 1533.0659874659361,
            "Richmond": 1475.5299927145738,
            "Melbourne": 1380.928843483692,
            "St Kilda": 1588.0480963788857,
            "Fitzroy": 1376.9160447075917,
            "Sydney": 1535.721783275861,
            "Hawthorn": 1443.4548221742657,
            "Collingwood": 1496.3946703307793,
            "Adelaide": 1560.4031317855142,
            "Fremantle": 1447.6568726947255,
            "Port Adelaide": 1480.1084647662378,
            "Gold Coast": 1500.0,
            "Greater Western Sydney": 1500.0
        },
        "1998": {
            "Carlton": 1518.5686926479548,
            "Essendon": 1522.3205218999794,
            "Geelong": 1451.823488649416,
            "North Melbourne": 1663.4474046633309,
            "Brisbane Lions": 1343.5206653796786,
            "West Coast": 1551.4221603110627,
            "Western Bulldogs": 1593.9050780805471,
            "Richmond": 1488.9994881279838,
            "Melbourne": 1564.6291880204353,
            "St Kilda": 1524.5650490586052,
            "Fitzroy": 1376.9160447075917,
            "Sydney": 1551.4037844156092,
            "Hawthorn": 1459.971727623072,
            "Collingwood": 1399.3524233732103,
            "Adelaide": 1703.6371204202342,
            "Fremantle": 1336.3071547601,
            "Port Adelaide": 1449.2100078611888,
            "Gold Coast": 1500.0,
            "Greater Western Sydney": 1500.0
        },
        "1999_start": {
            "Carlton": 1511.1412155887729,
            "Essendon": 1513.3923131399877,
            "Geelong": 1471.0940931896496,
            "North Melbourne": 1598.0684427979986,
            "Brisbane Lions": 1406.1123992278071,
            "West Coast": 1530.8532961866376,
            "Western Bulldogs": 1556.3430468483282,
            "Richmond": 1493.3996928767904,
            "Melbourne": 1538.7775128122612,
            "St Kilda": 1514.739029435163,
            "Fitzroy": 1426.149626824555,
            "Sydney": 1530.8422706493654,
            "Hawthorn": 1475.9830365738433,
            "Collingwood": 1439.6114540239262,
            "Adelaide": 1622.1822722521406,
            "Fremantle": 1401.7842928560601,
            "Port Adelaide": 1469.5260047167133,
            "Gold Coast": 1500.0,
            "Greater Western Sydney": 1500.0
        },
        "1999": {
            "Carlton": 1532.0079462895858,
            "Essendon": 1688.4799224126805,
            "Geelong": 1461.309651646245,
            "North Melbourne": 1713.4152962041726,
            "Brisbane Lions": 1666.3917427821134,
            "West Coast": 1490.1062913053468,
            "Western Bulldogs": 1648.6946003698915,
            "Richmond": 1447.5810155218137,
            "Melbourne": 1347.09576009209,
            "St Kilda": 1476.468363276003,
            "Fitzroy": 1426.149626824555,
            "Sydney": 1521.740257496061,
            "Hawthorn": 1458.6590173391112,
            "Collingwood": 1361.3706351134272,
            "Adelaide": 1446.393442066165,
            "Fremantle": 1349.1126173534171,
            "Port Adelaide": 1465.0238139073215,
            "Gold Coast": 1500.0,
            "Greater Western Sydney": 1500.0
        },
        "2000_start": {
            "Carlton": 1519.2047677737514,
            "Essendon": 1613.0879534476082,
            "Geelong": 1476.7857909877469,
            "North Melbourne": 1628.0491777225036,
            "Brisbane Lions": 1599.835045669268,
            "West Coast": 1494.0637747832081,
            "Western Bulldogs": 1589.216760221935,
            "Richmond": 1468.5486093130883,
            "Melbourne": 1408.257456055254,
            "St Kilda": 1485.8810179656018,
            "Fitzroy": 1455.6897760947331,
            "Sydney": 1513.0441544976366,
            "Hawthorn": 1475.1954104034667,
            "Collingwood": 1416.8223810680563,
            "Adelaide": 1467.836065239699,
            "Fremantle": 1409.4675704120502,
            "Port Adelaide": 1479.014288344393,
            "Gold Coast": 1500.0,
            "Greater Western Sydney": 1500.0
        },
        "2000": {
            "Carlton": 1673.2690377635968,
            "Essendon": 1833.1808449657426,
            "Geelong": 1458.4156914688924,
            "North Melbourne": 1558.114515068873,
            "Brisbane Lions": 1597.517687595635,
            "West Coast": 1376.4128577579336,
            "Western Bulldogs": 1537.085097621455,
            "Richmond": 1491.8903003742744,
            "Melbourne": 1603.211311236148,
            "St Kilda": 1283.922554174375,
            "Fitzroy": 1455.6897760947331,
            "Sydney": 1509.192154192089,
            "Hawthorn": 1535.0689998562957,
            "Collingwood": 1356.8891071373093,
            "Adelaide": 1440.9273586207378,
            "Fremantle": 1348.5813999103189,
            "Port Adelaide": 1440.6313061615908,
            "Gold Coast": 1500.0,
            "Greater Western Sydney": 1500.0
        },
        "2001_start": {
            "Carlton": 1603.961422658158,
            "Essendon": 1699.9085069794455,
            "Geelong": 1475.0494148813355,
            "North Melbourne": 1534.8687090413239,
            "Brisbane Lions": 1558.510612557381,
            "West Coast": 1425.8477146547602,
            "Western Bulldogs": 1522.251058572873,
            "Richmond": 1495.1341802245647,
            "Melbourne": 1561.9267867416888,
            "St Kilda": 1370.353532504625,
            "Fitzroy": 1473.4138656568398,
            "Sydney": 1505.5152925152533,
            "Hawthorn": 1521.0413999137775,
            "Collingwood": 1414.1334642823856,
            "Adelaide": 1464.5564151724427,
            "Fremantle": 1409.1488399461914,
            "Port Adelaide": 1464.3787836969545,
            "Gold Coast": 1500.0,
            "Greater Western Sydney": 1500.0
        },
        "2001": {
            "Carlton": 1635.8191746600442,
            "Essendon": 1729.0099853046186,
            "Geelong": 1446.6114968025872,
            "North Melbourne": 1468.959261337688,
            "Brisbane Lions": 1753.7951196580839,
            "West Coast": 1307.4579987409345,
            "Western Bulldogs": 1481.0315582491592,
            "Richmond": 1566.998626039598,
            "Melbourne": 1466.143875578982,
            "St Kilda": 1244.1330171585537,
            "Fitzroy": 1473.4138656568398,
            "Sydney": 1519.273976786157,
            "Hawthorn": 1545.7624362453478,
            "Collingwood": 1485.7683815041637,
            "Adelaide": 1507.2928256641912,
            "Fremantle": 1267.7011418619813,
            "Port Adelaide": 1600.8272587510705,
            "Gold Coast": 1500.0,
            "Greater Western Sydney": 1500.0
        },
        "2002_start": {
            "Carlton": 1581.4915047960264,
            "Essendon": 1637.4059911827712,
            "Geelong": 1467.9668980815522,
            "North Melbourne": 1481.375556802613,
            "Brisbane Lions": 1652.2770717948504,
            "West Coast": 1384.4747992445607,
            "Western Bulldogs": 1488.6189349494955,
            "Richmond": 1540.199175623759,
            "Melbourne": 1479.6863253473891,
            "St Kilda": 1346.4798102951322,
            "Fitzroy": 1484.0483193941038,
            "Sydney": 1511.5643860716941,
            "Hawthorn": 1527.4574617472088,
            "Collingwood": 1491.4610289024981,
            "Adelaide": 1504.3756953985148,
            "Fremantle": 1360.6206851171887,
            "Port Adelaide": 1560.4963552506424,
            "Gold Coast": 1500.0,
            "Greater Western Sydney": 1500.0
        },
        "2002": {
            "Carlton": 1321.718272129796,
            "Essendon": 1563.5271696418824,
            "Geelong": 1458.5757258388617,
            "North Melbourne": 1480.4245193447657,
            "Brisbane Lions": 1773.3928667677462,
            "West Coast": 1442.5208747494169,
            "Western Bulldogs": 1519.2957333630943,
            "Richmond": 1417.0688826622522,
            "Melbourne": 1497.2916148489944,
            "St Kilda": 1329.5617590751392,
            "Fitzroy": 1484.0483193941038,
            "Sydney": 1542.1017674911948,
            "Hawthorn": 1490.7200949824494,
            "Collingwood": 1542.90664816504,
            "Adelaide": 1580.3006755430074,
            "Fremantle": 1390.8053514084927,
            "Port Adelaide": 1665.7397245937627,
            "Gold Coast": 1500.0,
            "Greater Western Sydney": 1500.0
        },
        "2003_start": {
            "Carlton": 1393.0309632778776,
            "Essendon": 1538.1163017851295,
            "Geelong": 1475.145435503317,
            "North Melbourne": 1488.2547116068595,
            "Brisbane Lions": 1664.0357200606477,
            "West Coast": 1465.5125248496502,
            "Western Bulldogs": 1511.5774400178566,
            "Richmond": 1450.2413295973513,
            "Melbourne": 1498.3749689093966,
            "St Kilda": 1397.7370554450836,
            "Fitzroy": 1490.4289916364623,
            "Sydney": 1525.261060494717,
            "Hawthorn": 1494.4320569894696,
            "Collingwood": 1525.743988899024,
            "Adelaide": 1548.1804053258045,
            "Fremantle": 1434.4832108450955,
            "Port Adelaide": 1599.4438347562577,
            "Gold Coast": 1500.0,
            "Greater Western Sydney": 1500.0
        },
        "2003": {
            "Carlton": 1254.4908615974316,
            "Essendon": 1593.6596243373192,
            "Geelong": 1414.1967130149017,
            "North Melbourne": 1492.4637743832373,
            "Brisbane Lions": 1731.1501088242428,
            "West Coast": 1524.6399652344967,
            "Western Bulldogs": 1309.372514295576,
            "Richmond": 1385.1701524472426,
            "Melbourne": 1338.9009298733386,
            "St Kilda": 1451.6880164203196,
            "Fitzroy": 1490.4289916364623,
            "Sydney": 1583.2748753392555,
            "Hawthorn": 1516.4052680009074,
            "Collingwood": 1633.715002320602,
            "Adelaide": 1605.5719252599501,
            "Fremantle": 1489.2738371608739,
            "Port Adelaide": 1685.5974398538433,
            "Gold Coast": 1500.0,
            "Greater Western Sydney": 1500.0
        },
        "2004_start": {
            "Carlton": 1352.694516958459,
            "Essendon": 1556.1957746023916,
            "Geelong": 1448.518027808941,
            "North Melbourne": 1495.4782646299423,
            "Brisbane Lions": 1638.6900652945458,
            "West Coast": 1514.783979140698,
            "Western Bulldogs": 1385.6235085773455,
            "Richmond": 1431.1020914683456,
            "Melbourne": 1403.3405579240032,
            "St Kilda": 1471.0128098521918,
            "Fitzroy": 1494.2573949818775,
            "Sydney": 1549.9649252035533,
            "Hawthorn": 1509.8431608005444,
            "Collingwood": 1580.2290013923612,
            "Adelaide": 1563.3431551559702,
            "Fremantle": 1493.5643022965244,
            "Port Adelaide": 1611.358463912306,
            "Gold Coast": 1500.0,
            "Greater Western Sydney": 1500.0
        },
        "2004": {
            "Carlton": 1393.3146461143685,
            "Essendon": 1529.1229581406967,
            "Geelong": 1587.332040357069,
            "North Melbourne": 1480.9685368756654,
            "Brisbane Lions": 1696.7022704592566,
            "West Coast": 1552.8764547266674,
            "Western Bulldogs": 1310.7942744557924,
            "Richmond": 1256.6222085478462,
            "Melbourne": 1496.5470366588518,
            "St Kilda": 1598.0362814089704,
            "Fitzroy": 1494.2573949818775,
            "Sydney": 1586.8067548136953,
            "Hawthorn": 1333.5699033156488,
            "Collingwood": 1479.224388184291,
            "Adelaide": 1507.4396716064691,
            "Fremantle": 1478.8240563427742,
            "Port Adelaide": 1717.5611230100603,
            "Gold Coast": 1500.0,
            "Greater Western Sydney": 1500.0
        },
        "2005_start": {
            "Carlton": 1435.9887876686212,
            "Essendon": 1517.473774884418,
            "Geelong": 1552.3992242142415,
            "North Melbourne": 1488.5811221253994,
            "Brisbane Lions": 1618.0213622755539,
            "West Coast": 1531.7258728360005,
            "Western Bulldogs": 1386.4765646734754,
            "Richmond": 1353.9733251287078,
            "Melbourne": 1497.928221995311,
            "St Kilda": 1558.8217688453822,
            "Fitzroy": 1496.5544369891265,
            "Sydney": 1552.0840528882172,
            "Hawthorn": 1400.1419419893894,
            "Collingwood": 1487.5346329105746,
            "Adelaide": 1504.4638029638816,
            "Fremantle": 1487.2944338056645,
            "Port Adelaide": 1630.536673806036,
            "Gold Coast": 1500.0,
            "Greater Western Sydney": 1500.0
        },
        "2005": {
            "Carlton": 1290.0598587126726,
            "Essendon": 1440.2235356074507,
            "Geelong": 1558.4662234373154,
            "North Melbourne": 1494.322463202138,
            "Brisbane Lions": 1541.2770261218025,
            "West Coast": 1617.3665993045615,
            "Western Bulldogs": 1501.6290975944023,
            "Richmond": 1362.6034028496701,
            "Melbourne": 1458.0244950184542,
            "St Kilda": 1632.6097606618653,
            "Fitzroy": 1496.5544369891265,
            "Sydney": 1671.2060869979043,
            "Hawthorn": 1350.898188755257,
            "Collingwood": 1359.0506465224037,
            "Adelaide": 1656.4800671068558,
            "Fremantle": 1479.278602101838,
            "Port Adelaide": 1589.949509016283,
            "Gold Coast": 1500.0,
            "Greater Western Sydney": 1500.0
        },
        "2006_start": {
            "Carlton": 1374.0359152276035,
            "Essendon": 1464.1341213644705,
            "Geelong": 1535.0797340623892,
            "North Melbourne": 1496.5934779212828,
            "Brisbane Lions": 1524.7662156730814,
            "West Coast": 1570.419959582737,
            "Western Bulldogs": 1500.9774585566413,
            "Richmond": 1417.562041709802,
            "Melbourne": 1474.8146970110724,
            "St Kilda": 1579.5658563971192,
            "Fitzroy": 1497.9326621934758,
            "Sydney": 1602.7236521987427,
            "Hawthorn": 1410.5389132531543,
            "Collingwood": 1415.4303879134422,
            "Adelaide": 1593.8880402641134,
            "Fremantle": 1487.567161261103,
            "Port Adelaide": 1553.9697054097699,
            "Gold Coast": 1500.0,
            "Greater Western Sydney": 1500.0
        },
        "2006": {
            "Carlton": 1251.7277048498681,
            "Essendon": 1333.722369317294,
            "Geelong": 1503.9997384554956,
            "North Melbourne": 1404.728844445409,
            "Brisbane Lions": 1382.5865164999539,
            "West Coast": 1682.558107568159,
            "Western Bulldogs": 1540.8921295141656,
            "Richmond": 1444.6000761146668,
            "Melbourne": 1559.4197104817763,
            "St Kilda": 1597.3429043064764,
            "Fitzroy": 1497.9326621934758,
            "Sydney": 1656.1628539237965,
            "Hawthorn": 1418.0182673201093,
            "Collingwood": 1508.463687233974,
            "Adelaide": 1670.2998617191288,
            "Fremantle": 1589.2449263298158,
            "Port Adelaide": 1458.2996397264355,
            "Gold Coast": 1500.0,
            "Greater Western Sydney": 1500.0
        },
        "2007_start": {
            "Carlton": 1351.0366229099209,
            "Essendon": 1400.2334215903763,
            "Geelong": 1502.3998430732975,
            "North Melbourne": 1442.8373066672455,
            "Brisbane Lions": 1429.5519098999723,
            "West Coast": 1609.5348645408953,
            "Western Bulldogs": 1524.5352777084993,
            "Richmond": 1466.7600456688,
            "Melbourne": 1535.6518262890659,
            "St Kilda": 1558.4057425838857,
            "Fitzroy": 1498.7595973160855,
            "Sydney": 1593.6977123542779,
            "Hawthorn": 1450.8109603920657,
            "Collingwood": 1505.0782123403844,
            "Adelaide": 1602.1799170314773,
            "Fremantle": 1553.5469557978895,
            "Port Adelaide": 1474.9797838358613,
            "Gold Coast": 1500.0,
            "Greater Western Sydney": 1500.0
        },
        "2007": {
            "Carlton": 1245.627317731577,
            "Essendon": 1370.7802806142738,
            "Geelong": 1751.0174284855889,
            "North Melbourne": 1530.4465679397165,
            "Brisbane Lions": 1477.9042753999563,
            "West Coast": 1581.6882431689053,
            "Western Bulldogs": 1414.9192513770408,
            "Richmond": 1350.2576063384327,
            "Melbourne": 1389.7502508585133,
            "St Kilda": 1526.9075837872108,
            "Fitzroy": 1498.7595973160855,
            "Sydney": 1593.8173656150925,
            "Hawthorn": 1528.764214702853,
            "Collingwood": 1550.212318855003,
            "Adelaide": 1593.8615051279762,
            "Fremantle": 1523.177482577682,
            "Port Adelaide": 1572.1087101040928,
            "Gold Coast": 1500.0,
            "Greater Western Sydney": 1500.0
        },
        "2008_start": {
            "Carlton": 1347.3763906389463,
            "Essendon": 1422.4681683685642,
            "Geelong": 1650.6104570913533,
            "North Melbourne": 1518.26794076383,
            "Brisbane Lions": 1486.7425652399738,
            "West Coast": 1549.012945901343,
            "Western Bulldogs": 1448.9515508262245,
            "Richmond": 1410.1545638030595,
            "Melbourne": 1433.850150515108,
            "St Kilda": 1516.1445502723266,
            "Fitzroy": 1499.2557583896514,
            "Sydney": 1556.2904193690556,
            "Hawthorn": 1517.2585288217117,
            "Collingwood": 1530.127391313002,
            "Adelaide": 1556.3169030767858,
            "Fremantle": 1513.9064895466092,
            "Port Adelaide": 1543.2652260624557,
            "Gold Coast": 1500.0,
            "Greater Western Sydney": 1500.0
        },
        "2008": {
            "Carlton": 1416.9931493636582,
            "Essendon": 1383.09182428735,
            "Geelong": 1785.400329359711,
            "North Melbourne": 1496.0258753251433,
            "Brisbane Lions": 1472.845108016115,
            "West Coast": 1333.2318863899889,
            "Western Bulldogs": 1568.805001983032,
            "Richmond": 1474.709955134398,
            "Melbourne": 1255.0885996878064,
            "St Kilda": 1560.6697425095542,
            "Fitzroy": 1499.2557583896514,
            "Sydney": 1537.2985586013708,
            "Hawthorn": 1694.408698101103,
            "Collingwood": 1550.885046383296,
            "Adelaide": 1546.8011088463254,
            "Fremantle": 1447.8430689390304,
            "Port Adelaide": 1476.6462886824668,
            "Gold Coast": 1500.0,
            "Greater Western Sydney": 1500.0
        },
        "2009_start": {
            "Carlton": 1450.195889618195,
            "Essendon": 1429.85509457241,
            "Geelong": 1671.2401976158264,
            "North Melbourne": 1497.6155251950859,
            "Brisbane Lions": 1483.707064809669,
            "West Coast": 1399.9391318339933,
            "Western Bulldogs": 1541.2830011898193,
            "Richmond": 1484.8259730806387,
            "Melbourne": 1353.0531598126838,
            "St Kilda": 1536.4018455057326,
            "Fitzroy": 1499.553455033791,
            "Sydney": 1522.3791351608224,
            "Hawthorn": 1616.6452188606618,
            "Collingwood": 1530.5310278299776,
            "Adelaide": 1528.0806653077952,
            "Fremantle": 1468.7058413634184,
            "Port Adelaide": 1485.98777320948,
            "Gold Coast": 1500.0,
            "Greater Western Sydney": 1500.0
        },
        "2009": {
            "Carlton": 1531.6521169877974,
            "Essendon": 1441.6543475326323,
            "Geelong": 1737.5104770867392,
            "North Melbourne": 1394.649559971998,
            "Brisbane Lions": 1553.2761134931573,
            "West Coast": 1404.1315030197366,
            "Western Bulldogs": 1661.3007419551,
            "Richmond": 1314.5990905737615,
            "Melbourne": 1282.0785328225857,
            "St Kilda": 1735.5425549516478,
            "Fitzroy": 1499.553455033791,
            "Sydney": 1455.911144604729,
            "Hawthorn": 1490.1370552651142,
            "Collingwood": 1596.3364149349793,
            "Adelaide": 1617.0669144268224,
            "Fremantle": 1372.669826620208,
            "Port Adelaide": 1411.9301507192008,
            "Gold Coast": 1500.0,
            "Greater Western Sydney": 1500.0
        },
        "2010_start": {
            "Carlton": 1518.9912701926785,
            "Essendon": 1464.9926085195793,
            "Geelong": 1642.5062862520435,
            "North Melbourne": 1436.7897359831989,
            "Brisbane Lions": 1531.9656680958944,
            "West Coast": 1442.478901811842,
            "Western Bulldogs": 1596.78044517306,
            "Richmond": 1388.759454344257,
            "Melbourne": 1369.2471196935514,
            "St Kilda": 1641.3255329709887,
            "Fitzroy": 1499.7320730202746,
            "Sydney": 1473.5466867628375,
            "Hawthorn": 1494.0822331590684,
            "Collingwood": 1557.8018489609876,
            "Adelaide": 1570.2401486560934,
            "Fremantle": 1423.6018959721248,
            "Port Adelaide": 1447.1580904315206,
            "Gold Coast": 1500.0,
            "Greater Western Sydney": 1500.0
        },
        "2010": {
            "Carlton": 1517.6785342586568,
            "Essendon": 1362.162747352163,
            "Geelong": 1719.6249412892316,
            "North Melbourne": 1469.0583099134533,
            "Brisbane Lions": 1402.7937047754183,
            "West Coast": 1315.2509840242137,
            "Western Bulldogs": 1606.314699981769,
            "Richmond": 1330.508170977762,
            "Melbourne": 1387.7944600256512,
            "St Kilda": 1641.1786014498239,
            "Fitzroy": 1499.7320730202746,
            "Sydney": 1563.2640601306864,
            "Hawthorn": 1526.4408872691524,
            "Collingwood": 1776.1438853049738,
            "Adelaide": 1491.164596542811,
            "Fremantle": 1484.6331295698799,
            "Port Adelaide": 1406.2562141140793,
            "Gold Coast": 1500.0,
            "Greater Western Sydney": 1500.0
        },
        "2011_start": {
            "Carlton": 1510.6071205551941,
            "Essendon": 1417.2976484112978,
            "Geelong": 1631.774964773539,
            "North Melbourne": 1481.434985948072,
            "Brisbane Lions": 1441.676222865251,
            "West Coast": 1389.1505904145283,
            "Western Bulldogs": 1563.7888199890615,
            "Richmond": 1398.3049025866571,
            "Melbourne": 1432.6766760153907,
            "St Kilda": 1584.7071608698943,
            "Fitzroy": 1499.8392438121648,
            "Sydney": 1537.9584360784118,
            "Hawthorn": 1515.8645323614915,
            "Collingwood": 1665.6863311829843,
            "Adelaide": 1494.6987579256866,
            "Fremantle": 1490.779877741928,
            "Port Adelaide": 1443.7537284684477,
            "Gold Coast": 1500.0,
            "Greater Western Sydney": 1500.0
        },
        "2011": {
            "Carlton": 1616.6204222403856,
            "Essendon": 1447.8430368033996,
            "Geelong": 1803.2271498849607,
            "North Melbourne": 1517.7018404379412,
            "Brisbane Lions": 1332.0753459028108,
            "West Coast": 1588.7519696548757,
            "Western Bulldogs": 1488.9499461125706,
            "Richmond": 1392.420302440735,
            "Melbourne": 1391.7438033780045,
            "St Kilda": 1599.6517532916105,
            "Fitzroy": 1499.8392438121648,
            "Sydney": 1563.231022492099,
            "Hawthorn": 1687.609671855612,
            "Collingwood": 1769.154416230915,
            "Adelaide": 1378.3344071871907,
            "Fremantle": 1407.8842479716843,
            "Port Adelaide": 1267.6635110902691,
            "Gold Coast": 1247.297909212771,
            "Greater Western Sydney": 1500.0
        },
        "2012_start": {
            "Carlton": 1569.9722533442314,
            "Essendon": 1468.7058220820397,
            "Geelong": 1681.9362899309765,
            "North Melbourne": 1510.6211042627647,
            "Brisbane Lions": 1399.2452075416866,
            "West Coast": 1553.2511817929253,
            "Western Bulldogs": 1493.3699676675424,
            "Richmond": 1435.452181464441,
            "Melbourne": 1435.0462820268026,
            "St Kilda": 1559.7910519749662,
            "Fitzroy": 1499.903546287299,
            "Sydney": 1537.9386134952595,
            "Hawthorn": 1612.5658031133673,
            "Collingwood": 1661.492649738549,
            "Adelaide": 1427.0006443123143,
            "Fremantle": 1444.7305487830106,
            "Port Adelaide": 1360.5981066541615,
            "Gold Coast": 1348.3787455276627,
            "Greater Western Sydney": 1500.0
        },
        "2012": {
            "Carlton": 1521.2512101692027,
            "Essendon": 1462.799385282025,
            "Geelong": 1680.024416727573,
            "North Melbourne": 1578.5249199635712,
            "Brisbane Lions": 1420.670356248204,
            "West Coast": 1612.0930133893112,
            "Western Bulldogs": 1317.2413263004266,
            "Richmond": 1529.3362985300173,
            "Melbourne": 1287.120733826108,
            "St Kilda": 1585.6625435256078,
            "Fitzroy": 1499.903546287299,
            "Sydney": 1705.258995420696,
            "Hawthorn": 1745.100089853321,
            "Collingwood": 1638.2314515476553,
            "Adelaide": 1592.4806539848664,
            "Fremantle": 1582.2757311545918,
            "Port Adelaide": 1277.292816466125,
            "Gold Coast": 1222.776221019789,
            "Greater Western Sydney": 1241.95629030361
        },
        "2013_start": {
            "Carlton": 1512.7507261015216,
            "Essendon": 1477.679631169215,
            "Geelong": 1608.0146500365438,
            "North Melbourne": 1547.1149519781427,
            "Brisbane Lions": 1452.4022137489223,
            "West Coast": 1567.2558080335866,
            "Western Bulldogs": 1390.344795780256,
            "Richmond": 1517.6017791180104,
            "Melbourne": 1372.2724402956649,
            "St Kilda": 1551.3975261153646,
            "Fitzroy": 1499.9421277723793,
            "Sydney": 1623.1553972524175,
            "Hawthorn": 1647.0600539119926,
            "Collingwood": 1582.9388709285931,
            "Adelaide": 1555.48839239092,
            "Fremantle": 1549.365438692755,
            "Port Adelaide": 1366.375689879675,
            "Gold Coast": 1333.6657326118734,
            "Greater Western Sydney": 1345.173774182166
        },
        "2013": {
            "Carlton": 1516.2587590221867,
            "Essendon": 1497.1736321283922,
            "Geelong": 1718.6266743845563,
            "North Melbourne": 1588.2588793549205,
            "Brisbane Lions": 1432.8432843927992,
            "West Coast": 1454.4787735561326,
            "Western Bulldogs": 1383.7576858698203,
            "Richmond": 1604.3021309306062,
            "Melbourne": 1178.9099239966945,
            "St Kilda": 1430.7707335662055,
            "Fitzroy": 1499.9421277723793,
            "Sydney": 1651.4026097501492,
            "Hawthorn": 1794.528613565655,
            "Collingwood": 1599.9900434771228,
            "Adelaide": 1520.6212075996407,
            "Fremantle": 1651.7485969252655,
            "Port Adelaide": 1478.3463187348066,
            "Gold Coast": 1325.5812205845968,
            "Greater Western Sydney": 1172.4587843880704
        },
        "2014_start": {
            "Carlton": 1509.755255413312,
            "Essendon": 1498.3041792770352,
            "Geelong": 1631.1760046307338,
            "North Melbourne": 1552.9553276129523,
            "Brisbane Lions": 1459.7059706356795,
            "West Coast": 1472.6872641336795,
            "Western Bulldogs": 1430.2546115218922,
            "Richmond": 1562.5812785583637,
            "Melbourne": 1307.3459543980166,
            "St Kilda": 1458.4624401397234,
            "Fitzroy": 1499.9652766634276,
            "Sydney": 1590.8415658500894,
            "Hawthorn": 1676.717168139393,
            "Collingwood": 1559.9940260862736,
            "Adelaide": 1512.3727245597845,
            "Fremantle": 1591.0491581551594,
            "Port Adelaide": 1487.007791240884,
            "Gold Coast": 1395.3487323507582,
            "Greater Western Sydney": 1303.4752706328422
        },
        "2014": {
            "Carlton": 1454.434116448853,
            "Essendon": 1535.6569224957718,
            "Geelong": 1634.6846223182147,
            "North Melbourne": 1588.0355780308682,
            "Brisbane Lions": 1371.8174500488499,
            "West Coast": 1531.2707904571337,
            "Western Bulldogs": 1364.8074853722765,
            "Richmond": 1548.7532346703404,
            "Melbourne": 1203.1755465660356,
            "St Kilda": 1294.4013914507082,
            "Fitzroy": 1499.9652766634276,
            "Sydney": 1715.4235073909265,
            "Hawthorn": 1785.9172106088022,
            "Collingwood": 1479.452688543789,
            "Adelaide": 1546.699320588519,
            "Fremantle": 1629.930527254369,
            "Port Adelaide": 1619.361364135551,
            "Gold Coast": 1395.8769903823684,
            "Greater Western Sydney": 1300.3359765731957
        },
        "2015_start": {
            "Carlton": 1472.6604698693118,
            "Essendon": 1521.394153497463,
            "Geelong": 1580.8107733909287,
            "North Melbourne": 1552.8213468185209,
            "Brisbane Lions": 1423.09047002931,
            "West Coast": 1518.7624742742803,
            "Western Bulldogs": 1418.8844912233658,
            "Richmond": 1529.2519408022042,
            "Melbourne": 1321.9053279396214,
            "St Kilda": 1376.640834870425,
            "Fitzroy": 1499.9791659980565,
            "Sydney": 1629.254104434556,
            "Hawthorn": 1671.5503263652813,
            "Collingwood": 1487.6716131262733,
            "Adelaide": 1528.0195923531114,
            "Fremantle": 1577.9583163526215,
            "Port Adelaide": 1571.6168184813305,
            "Gold Coast": 1437.526194229421,
            "Greater Western Sydney": 1380.2015859439175
        },
        "2015": {
            "Carlton": 1301.6621075916955,
            "Essendon": 1342.7350804357475,
            "Geelong": 1559.55537680842,
            "North Melbourne": 1603.8245785502309,
            "Brisbane Lions": 1287.9238476665291,
            "West Coast": 1686.0004422146733,
            "Western Bulldogs": 1527.7102186035263,
            "Richmond": 1619.6238622382295,
            "Melbourne": 1333.139134698585,
            "St Kilda": 1340.919895828813,
            "Fitzroy": 1499.9791659980565,
            "Sydney": 1631.6205200832023,
            "Hawthorn": 1778.5786794387225,
            "Collingwood": 1489.206558522245,
            "Adelaide": 1572.8564816361943,
            "Fremantle": 1616.0293619294675,
            "Port Adelaide": 1587.6677392357471,
            "Gold Coast": 1305.853271814957,
            "Greater Western Sydney": 1415.1136767049577
        },
        "2016_start": {
            "Carlton": 1380.9972645550174,
            "Essendon": 1405.6410482614485,
            "Geelong": 1535.7332260850521,
            "North Melbourne": 1562.2947471301386,
            "Brisbane Lions": 1372.7543085999175,
            "West Coast": 1611.600265328804,
            "Western Bulldogs": 1516.6261311621158,
            "Richmond": 1571.7743173429378,
            "Melbourne": 1399.883480819151,
            "St Kilda": 1404.5519374972878,
            "Fitzroy": 1499.987499598834,
            "Sydney": 1578.9723120499214,
            "Hawthorn": 1667.1472076632335,
            "Collingwood": 1493.5239351133469,
            "Adelaide": 1543.7138889817165,
            "Fremantle": 1569.6176171576806,
            "Port Adelaide": 1552.6006435414483,
            "Gold Coast": 1383.5119630889742,
            "Greater Western Sydney": 1449.0682060229747
        },
        "2016": {
            "Carlton": 1321.4247551296642,
            "Essendon": 1246.5931097869366,
            "Geelong": 1654.900832676632,
            "North Melbourne": 1523.1201340000903,
            "Brisbane Lions": 1226.0724942851496,
            "West Coast": 1632.995219225049,
            "Western Bulldogs": 1652.4009332426117,
            "Richmond": 1452.2381405621136,
            "Melbourne": 1449.329018653585,
            "St Kilda": 1474.0327789829753,
            "Fitzroy": 1499.987499598834,
            "Sydney": 1709.8411005188536,
            "Hawthorn": 1654.4082919939983,
            "Collingwood": 1468.794447275139,
            "Adelaide": 1657.3757157365612,
            "Fremantle": 1373.5696739319585,
            "Port Adelaide": 1518.44103459922,
            "Gold Coast": 1321.1929919441222,
            "Greater Western Sydney": 1663.2818278565069
        },
        "2017_start": {
            "Carlton": 1392.8548530777985,
            "Essendon": 1347.955865872162,
            "Geelong": 1592.9404996059793,
            "North Melbourne": 1513.872080400054,
            "Brisbane Lions": 1335.6434965710898,
            "West Coast": 1579.7971315350294,
            "Western Bulldogs": 1591.440559945567,
            "Richmond": 1471.342884337268,
            "Melbourne": 1469.597411192151,
            "St Kilda": 1484.4196673897852,
            "Fitzroy": 1499.9924997593002,
            "Sydney": 1625.9046603113122,
            "Hawthorn": 1592.644975196399,
            "Collingwood": 1481.2766683650834,
            "Adelaide": 1594.4254294419368,
            "Fremantle": 1424.141804359175,
            "Port Adelaide": 1511.064620759532,
            "Gold Coast": 1392.7157951664733,
            "Greater Western Sydney": 1597.969096713904
        },
        "2017": {
            "Carlton": 1316.6297200350366,
            "Essendon": 1481.5084072003633,
            "Geelong": 1611.599222427016,
            "North Melbourne": 1400.060632711151,
            "Brisbane Lions": 1268.2557359582015,
            "West Coast": 1557.4293489667161,
            "Western Bulldogs": 1516.502256060679,
            "Richmond": 1674.635940471547,
            "Melbourne": 1520.6873458254013,
            "St Kilda": 1487.694337545337,
            "Fitzroy": 1499.9924997593002,
            "Sydney": 1673.825950314049,
            "Hawthorn": 1515.8452774049395,
            "Collingwood": 1466.5124696059365,
            "Adelaide": 1664.9666392446873,
            "Fremantle": 1332.7440506934595,
            "Port Adelaide": 1582.0313366870146,
            "Gold Coast": 1297.5787128880959,
            "Greater Western Sydney": 1631.5001162010694
        },
        "2018_start": {
            "Carlton": 1389.9778320210219,
            "Essendon": 1488.905044320218,
            "Geelong": 1566.9595334562096,
            "North Melbourne": 1440.0363796266906,
            "Brisbane Lions": 1360.9534415749208,
            "West Coast": 1534.4576093800297,
            "Western Bulldogs": 1509.9013536364073,
            "Richmond": 1604.7815642829282,
            "Melbourne": 1512.4124074952408,
            "St Kilda": 1492.6166025272023,
            "Fitzroy": 1499.9954998555802,
            "Sydney": 1604.2955701884293,
            "Hawthorn": 1509.5071664429636,
            "Collingwood": 1479.907481763562,
            "Adelaide": 1598.9799835468123,
            "Fremantle": 1399.6464304160756,
            "Port Adelaide": 1549.2188020122087,
            "Gold Coast": 1378.5472277328574,
            "Greater Western Sydney": 1578.9000697206416
        },
        "2018": {
            "Carlton": 1214.0996598046002,
            "Essendon": 1569.4332442755924,
            "Geelong": 1593.0061593963514,
            "North Melbourne": 1497.231703502391,
            "Brisbane Lions": 1356.6074989430826,
            "West Coast": 1652.4745696425466,
            "Western Bulldogs": 1409.348315931463,
            "Richmond": 1699.0356714339896,
            "Melbourne": 1640.3558359044662,
            "St Kilda": 1319.1359134710244,
            "Fitzroy": 1499.9954998555802,
            "Sydney": 1582.9569358768802,
            "Hawthorn": 1551.703759518483,
            "Collingwood": 1625.9495434383516,
            "Adelaide": 1554.0642900343585,
            "Fremantle": 1349.361016120797,
            "Port Adelaide": 1536.28093222533,
            "Gold Coast": 1257.2461623078643,
            "Greater Western Sydney": 1591.7132883168474
        },
        "2019_start": {
            "Carlton": 1328.45979588276,
            "Essendon": 1541.6599465653555,
            "Geelong": 1555.803695637811,
            "North Melbourne": 1498.3390221014345,
            "Brisbane Lions": 1413.9644993658496,
            "West Coast": 1591.484741785528,
            "Western Bulldogs": 1445.6089895588777,
            "Richmond": 1619.4214028603938,
            "Melbourne": 1584.2135015426798,
            "St Kilda": 1391.4815480826146,
            "Fitzroy": 1499.9972999133481,
            "Sydney": 1549.7741615261282,
            "Hawthorn": 1531.0222557110897,
            "Collingwood": 1575.5697260630109,
            "Adelaide": 1532.438574020615,
            "Fremantle": 1409.6166096724783,
            "Port Adelaide": 1521.768559335198,
            "Gold Coast": 1354.3476973847187,
            "Greater Western Sydney": 1555.0279729901085
        },
        "2019": {
            "Carlton": 1343.5789036204908,
            "Essendon": 1506.1892274407826,
            "Geelong": 1640.209792309132,
            "North Melbourne": 1528.1321560120712,
            "Brisbane Lions": 1551.828063587056,
            "West Coast": 1615.0074142806336,
            "Western Bulldogs": 1525.841066565062,
            "Richmond": 1706.3257515803157,
            "Melbourne": 1377.6780543151267,
            "St Kilda": 1352.9218710258,
            "Fitzroy": 1499.9972999133481,
            "Sydney": 1491.854352075761,
            "Hawthorn": 1571.388040815313,
            "Collingwood": 1622.5159626554387,
            "Adelaide": 1470.947374297772,
            "Fremantle": 1396.3227164305913,
            "Port Adelaide": 1534.527840736862,
            "Gold Coast": 1215.3984410345195,
            "Greater Western Sydney": 1549.3356713039243
        },
        "2020_start": {
            "Carlton": 1406.1473421722944,
            "Essendon": 1503.7135364644696,
            "Geelong": 1584.125875385479,
            "North Melbourne": 1516.8792936072427,
            "Brisbane Lions": 1531.0968381522337,
            "West Coast": 1569.0044485683802,
            "Western Bulldogs": 1515.5046399390371,
            "Richmond": 1623.7954509481895,
            "Melbourne": 1426.606832589076,
            "St Kilda": 1411.7531226154802,
            "Fitzroy": 1499.998379948009,
            "Sydney": 1495.1126112454565,
            "Hawthorn": 1542.8328244891877,
            "Collingwood": 1573.5095775932632,
            "Adelaide": 1482.5684245786633,
            "Fremantle": 1437.7936298583547,
            "Port Adelaide": 1520.7167044421171,
            "Gold Coast": 1329.2390646207116,
            "Greater Western Sydney": 1529.6014027823546
        },
        "2020": {
            "Carlton": 1398.5123799517387,
            "Essendon": 1436.530609730132,
            "Geelong": 1673.6270501804254,
            "North Melbourne": 1362.600991267467,
            "Brisbane Lions": 1610.6084339027477,
            "West Coast": 1612.5689355974223,
            "Western Bulldogs": 1547.7378385519994,
            "Richmond": 1710.4367294329732,
            "Melbourne": 1482.9028203001246,
            "St Kilda": 1526.244756046298,
            "Fitzroy": 1499.998379948009,
            "Sydney": 1417.302412286802,
            "Hawthorn": 1426.4543889966292,
            "Collingwood": 1555.8358315590535,
            "Adelaide": 1354.919710927178,
            "Fremantle": 1434.13159861071,
            "Port Adelaide": 1628.0090639157302,
            "Gold Coast": 1335.3027864008768,
            "Greater Western Sydney": 1486.2752823936833
        },
        "2021_start": {
            "Carlton": 1439.1074279710433,
            "Essendon": 1461.9183658380791,
            "Geelong": 1604.1762301082551,
            "North Melbourne": 1417.5605947604802,
            "Brisbane Lions": 1566.3650603416486,
            "West Coast": 1567.5413613584533,
            "Western Bulldogs": 1528.6427031311996,
            "Richmond": 1626.2620376597838,
            "Melbourne": 1489.7416921800748,
            "St Kilda": 1515.7468536277788,
            "Fitzroy": 1499.9990279688054,
            "Sydney": 1450.3814473720813,
            "Hawthorn": 1455.8726333979776,
            "Collingwood": 1533.5014989354322,
            "Adelaide": 1412.9518265563067,
            "Fremantle": 1460.478959166426,
            "Port Adelaide": 1576.8054383494382,
            "Gold Coast": 1401.1816718405262,
            "Greater Western Sydney": 1491.76516943621
        },
        "2021": {
            "Carlton": 1395.8010492998499,
            "Essendon": 1511.343934316865,
            "Geelong": 1646.8598582290342,
            "North Melbourne": 1301.4688368564841,
            "Brisbane Lions": 1612.6516538528247,
            "West Coast": 1471.3326099036228,
            "Western Bulldogs": 1636.1148423663203,
            "Richmond": 1523.4074807200298,
            "Melbourne": 1718.9079212818515,
            "St Kilda": 1516.3277483850247,
            "Fitzroy": 1499.9990279688054,
            "Sydney": 1576.4668422294305,
            "Hawthorn": 1404.1697319459918,
            "Collingwood": 1411.8398539254886,
            "Adelaide": 1350.646886579908,
            "Fremantle": 1414.4457833098957,
            "Port Adelaide": 1624.638546182845,
            "Gold Coast": 1353.6640526933932,
            "Greater Western Sydney": 1529.9133399523355
        },
        "2022_start": {
            "Carlton": 1437.4806295799099,
            "Essendon": 1506.806360590119,
            "Geelong": 1588.1159149374205,
            "North Melbourne": 1380.8813021138906,
            "Brisbane Lions": 1567.590992311695,
            "West Coast": 1482.7995659421738,
            "Western Bulldogs": 1581.6689054197923,
            "Richmond": 1514.044488432018,
            "Melbourne": 1631.344752769111,
            "St Kilda": 1509.7966490310148,
            "Fitzroy": 1499.9994167812833,
            "Sydney": 1545.8801053376583,
            "Hawthorn": 1442.501839167595,
            "Collingwood": 1447.1039123552932,
            "Adelaide": 1410.3881319479447,
            "Fremantle": 1448.6674699859375,
            "Port Adelaide": 1574.783127709707,
            "Gold Coast": 1412.1984316160358,
            "Greater Western Sydney": 1517.9480039714012
        },
        "2022": {
            "Carlton": 1489.9304149304742,
            "Essendon": 1404.5496817710018,
            "Geelong": 1759.5994565992835,
            "North Melbourne": 1194.3657249280982,
            "Brisbane Lions": 1626.6725438258632,
            "West Coast": 1251.9136213682611,
            "Western Bulldogs": 1567.933595467277,
            "Richmond": 1615.5218569076405,
            "Melbourne": 1654.5567738754003,
            "St Kilda": 1487.595855540712,
            "Fitzroy": 1499.9994167812833,
            "Sydney": 1661.773445567841,
            "Hawthorn": 1398.6939682960408,
            "Collingwood": 1549.7766514297725,
            "Adelaide": 1372.8160007308556,
            "Fremantle": 1556.3860710277834,
            "Port Adelaide": 1546.7066756041127,
            "Gold Coast": 1448.3039571932684,
            "Greater Western Sydney": 1412.9042881550313
        },
        "2023_start": {
            "Carlton": 1493.9582489582845,
            "Essendon": 1442.7298090626011,
            "Geelong": 1655.7596739595701,
            "North Melbourne": 1316.6194349568589,
            "Brisbane Lions": 1576.003526295518,
            "West Coast": 1351.1481728209567,
            "Western Bulldogs": 1540.7601572803662,
            "Richmond": 1569.3131141445842,
            "Melbourne": 1592.73406432524,
            "St Kilda": 1492.5575133244272,
            "Fitzroy": 1499.99965006877,
            "Sydney": 1597.0640673407047,
            "Hawthorn": 1439.2163809776246,
            "Collingwood": 1529.8659908578636,
            "Adelaide": 1423.6896004385135,
            "Fremantle": 1533.83164261667,
            "Port Adelaide": 1528.0240053624675,
            "Gold Coast": 1468.9823743159611,
            "Greater Western Sydney": 1447.7425728930189
        },
        "2023": {
            "Carlton": 1558.425727333211,
            "Essendon": 1427.819013943001,
            "Geelong": 1567.763987409041,
            "North Melbourne": 1222.249275021388,
            "Brisbane Lions": 1669.8033156987551,
            "West Coast": 1199.1171658210271,
            "Western Bulldogs": 1572.364471741824,
            "Richmond": 1497.6507382454326,
            "Melbourne": 1656.6168674332798,
            "St Kilda": 1509.5196755766178,
            "Fitzroy": 1499.99965006877,
            "Sydney": 1564.898597919517,
            "Hawthorn": 1376.0902860442127,
            "Collingwood": 1639.4544555427547,
            "Adelaide": 1509.4313253003927,
            "Fremantle": 1475.123345572564,
            "Port Adelaide": 1561.5426064679261,
            "Gold Coast": 1426.8239677398285,
            "Greater Western Sydney": 1565.3055271204578
        },
        "2024_start": {
            "Carlton": 1535.0554363999265,
            "Essendon": 1456.6914083658005,
            "Geelong": 1540.6583924454246,
            "North Melbourne": 1333.3495650128327,
            "Brisbane Lions": 1601.8819894192532,
            "West Coast": 1319.4702994926163,
            "Western Bulldogs": 1543.4186830450944,
            "Richmond": 1498.5904429472596,
            "Melbourne": 1593.9701204599678,
            "St Kilda": 1505.7118053459708,
            "Fitzroy": 1499.999790041262,
            "Sydney": 1538.9391587517102,
            "Hawthorn": 1425.6541716265276,
            "Collingwood": 1583.6726733256528,
            "Adelaide": 1505.6587951802355,
            "Fremantle": 1485.0740073435384,
            "Port Adelaide": 1536.9255638807556,
            "Gold Coast": 1456.094380643897,
            "Greater Western Sydney": 1539.1833162722746
        },
        "2024": {
            "Carlton": 1546.950358419568,
            "Essendon": 1439.7324844279294,
            "Geelong": 1598.5346980644315,
            "North Melbourne": 1223.3189961886515,
            "Brisbane Lions": 1701.6403858667338,
            "West Coast": 1261.2065026513835,
            "Western Bulldogs": 1599.5119538814954,
            "Richmond": 1250.2796363011628,
            "Melbourne": 1522.6557745965865,
            "St Kilda": 1494.124790923327,
            "Fitzroy": 1499.999790041262,
            "Sydney": 1652.6830759608258,
            "Hawthorn": 1600.0973172102604,
            "Collingwood": 1554.043572178301,
            "Adelaide": 1458.5256465856844,
            "Fremantle": 1525.3915820093785,
            "Port Adelaide": 1553.5301851904821,
            "Gold Coast": 1445.7893490719068,
            "Greater Western Sydney": 1571.98390043063
        },
        "2025_start": {
            "Carlton": 1528.1702150517408,
            "Essendon": 1463.8394906567576,
            "Geelong": 1559.1208188386588,
            "North Melbourne": 1333.991397713191,
            "Brisbane Lions": 1620.9842315200403,
            "West Coast": 1356.72390159083,
            "Western Bulldogs": 1559.7071723288973,
            "Richmond": 1350.1677817806976,
            "Melbourne": 1513.593464757952,
            "St Kilda": 1496.4748745539962,
            "Fitzroy": 1499.9998740247572,
            "Sydney": 1591.6098455764954,
            "Hawthorn": 1560.0583903261563,
            "Collingwood": 1532.4261433069805,
            "Adelaide": 1475.1153879514106,
            "Fremantle": 1515.2349492056271,
            "Port Adelaide": 1532.1181111142894,
            "Gold Coast": 1467.4736094431441,
            "Greater Western Sydney": 1543.190340258378
        },
        "2025": {
            "Carlton": 1458.9485770742947,
            "Essendon": 1319.414138502917,
            "Geelong": 1676.596852023122,
            "North Melbourne": 1288.6320942059888,
            "Brisbane Lions": 1751.0496152873761,
            "West Coast": 1183.1184072137235,
            "Western Bulldogs": 1618.0401411740922,
            "Richmond": 1258.9824716062067,
            "Melbourne": 1417.8432271281033,
            "St Kilda": 1416.1894403732292,
            "Fitzroy": 1499.9998740247572,
            "Sydney": 1520.9336586742525,
            "Hawthorn": 1654.947395359763,
            "Collingwood": 1626.034040513748,
            "Adelaide": 1617.8164493456968,
            "Fremantle": 1585.7120463641018,
            "Port Adelaide": 1432.2293684799383,
            "Gold Coast": 1567.75176380396,
            "Greater Western Sydney": 1605.7604388447294
        }
    },
    "model_type": "win_elo",
    "last_updated": "2026-03-06T18:40:17.284874",
    "performance_metrics": {
        "accuracy": 0.6770954598370198,
        "brier_score": 0.20271181154022946,
        "log_loss": 0.5890161493714781,
        "bits_score_per_game": 0.15022932229825445,
        "bits_score_total": 1032.3759028336046
    }
}